{"frameRate":24,"isGlobal":0,"armature":[{"skin":[{"name":"","slot":[{"display":[{"path":"ini1","type":"image","name":"ini1","transform":{"y":12.8888,"skX":92.4819,"skY":92.4819,"x":156.4886}},{"path":"ini2","type":"image","name":"ini2","transform":{"y":5.9234,"skX":92.4819,"skY":92.4819,"x":190.9912}},{"path":"ini3","type":"image","name":"ini3","transform":{"y":-5.5208,"skX":92.4819,"skY":92.4819,"x":279.4236}}],"name":"ini1"}]}],"type":"Armature","bone":[{"name":"root","transform":{}},{"length":456,"transform":{"y":-180.1,"skX":-92.4819,"skY":-92.4819,"x":390.9},"parent":"root","name":"ini1"}],"aabb":{"width":496,"y":-753.0223795894672,"height":588,"x":125.28412585470687},"ik":[],"animation":[{"duration":18,"frame":[],"bone":[{"frame":[{"duration":18,"transform":{}}],"name":"root"},{"frame":[{"duration":18,"transform":{}}],"name":"ini1"}],"slot":[{"frame":[{"tweenEasing":null,"duration":6},{"tweenEasing":null,"duration":6,"displayIndex":1},{"tweenEasing":null,"duration":6,"displayIndex":2},{"tweenEasing":null,"duration":0,"displayIndex":2}],"name":"ini1"}],"ffd":[],"ik":[],"playTimes":0,"name":"animtion0"}],"defaultActions":[{"gotoAndPlay":"animtion0"}],"name":"Armature","frameRate":24,"slot":[{"color":{},"name":"ini1","parent":"ini1","displayIndex":2},{"z":1,"color":{},"name":"ini2","parent":"root","displayIndex":-1},{"z":2,"color":{},"name":"ini3","parent":"root","displayIndex":-1}]}],"name":"inimigoexp","version":"5.0"}